wavelink-stubs/__init__.pyi
wavelink-stubs/backoff.pyi
wavelink-stubs/enums.pyi
wavelink-stubs/exceptions.pyi
wavelink-stubs/filters.pyi
wavelink-stubs/node.pyi
wavelink-stubs/payloads.pyi
wavelink-stubs/player.pyi
wavelink-stubs/queue.pyi
wavelink-stubs/tracks.pyi
wavelink-stubs/websocket.pyi
wavelink-stubs/ext/spotify/__init__.pyi
wavelink-stubs/ext/spotify/utils.pyi
wavelink-stubs/types/events.pyi
wavelink-stubs/types/request.pyi
wavelink-stubs/types/state.pyi
wavelink-stubs/types/track.pyi
wavelink_stubs-2.6.5.dist-info/LICENSE
wavelink_stubs-2.6.5.dist-info/METADATA
wavelink_stubs-2.6.5.dist-info/WHEEL
wavelink_stubs-2.6.5.dist-info/top_level.txt
wavelink_stubs-2.6.5.dist-info/RECORD
