Metadata-Version: 2.1
Name: wavelink-stubs
Version: 2.6.5
Summary: Type stubs for wavelink 2.
Author-email: Sachaa-Thanasius <111999343+Sachaa-Thanasius@users.noreply.github.com>
License: MIT License
Project-URL: Repository, https://github.com/Sachaa-Thanasius/wavelink-stubs
Project-URL: Bug Tracker, https://github.com/Sachaa-Thanasius/wavelink-stubs/issues
Keywords: python,python-3,wavelink,type-stubs
Classifier: Development Status :: 1 - Planning
Classifier: Intended Audience :: Developers
Classifier: License :: OSI Approved :: MIT License
Classifier: Natural Language :: English
Classifier: Operating System :: OS Independent
Classifier: Programming Language :: Python
Classifier: Programming Language :: Python :: 3
Classifier: Programming Language :: Python :: 3.10
Classifier: Programming Language :: Python :: 3.11
Classifier: Typing :: Typed
Requires-Python: >=3.10
License-File: LICENSE
Requires-Dist: wavelink <2.6.6,>=2.6.3
Requires-Dist: discord.py >=2.0.1
Requires-Dist: typing-extensions >=4.8.0
Provides-Extra: dev
Requires-Dist: black ; extra == 'dev'
Requires-Dist: ruff ; extra == 'dev'
Requires-Dist: pre-commit ; extra == 'dev'
